jupyterlab_comments/__init__.py
jupyterlab_comments/_version.py
jupyterlab_comments/labextension/package.json
jupyterlab_comments/labextension/static/534.5bacd53ff8abde753fd3.js
jupyterlab_comments/labextension/static/928.91df99834cfbcbfa373a.js
jupyterlab_comments/labextension/static/remoteEntry.6571c35ed422a118f5d8.js
jupyterlab_comments/labextension/static/style.js
jupyterlab_comments/labextension/static/third-party-licenses.json
jupyterlab_comments-0.1.2.data/data/share/jupyter/labextensions/jupyterlab-comments/install.json
jupyterlab_comments-0.1.2.data/data/share/jupyter/labextensions/jupyterlab-comments/package.json
jupyterlab_comments-0.1.2.data/data/share/jupyter/labextensions/jupyterlab-comments/static/534.5bacd53ff8abde753fd3.js
jupyterlab_comments-0.1.2.data/data/share/jupyter/labextensions/jupyterlab-comments/static/928.91df99834cfbcbfa373a.js
jupyterlab_comments-0.1.2.data/data/share/jupyter/labextensions/jupyterlab-comments/static/remoteEntry.6571c35ed422a118f5d8.js
jupyterlab_comments-0.1.2.data/data/share/jupyter/labextensions/jupyterlab-comments/static/style.js
jupyterlab_comments-0.1.2.data/data/share/jupyter/labextensions/jupyterlab-comments/static/third-party-licenses.json
jupyterlab_comments-0.1.2.dist-info/LICENSE
jupyterlab_comments-0.1.2.dist-info/METADATA
jupyterlab_comments-0.1.2.dist-info/WHEEL
jupyterlab_comments-0.1.2.dist-info/top_level.txt
jupyterlab_comments-0.1.2.dist-info/RECORD
